blackboard/__init__.py
blackboard/__main__.py
blackboard/cli.py
blackboard/config.py
blackboard/core.py
blackboard/decorators.py
blackboard/embeddings.py
blackboard/evals.py
blackboard/events.py
blackboard/flow.py
blackboard/graph.py
blackboard/hierarchy.py
blackboard/llm.py
blackboard/logging.py
blackboard/map_reduce.py
blackboard/mcp.py
blackboard/memory.py
blackboard/merging.py
blackboard/middleware.py
blackboard/optimize.py
blackboard/patching.py
blackboard/patterns.py
blackboard/pricing.py
blackboard/prompts.py
blackboard/protocols.py
blackboard/reasoning.py
blackboard/replay.py
blackboard/retry.py
blackboard/runtime.py
blackboard/sandbox.py
blackboard/schemas.py
blackboard/state.py
blackboard/streaming.py
blackboard/telemetry.py
blackboard/tools.py
blackboard/tui.py
blackboard/tui_legacy.py
blackboard/usage.py
blackboard/vectordb.py
blackboard/integrations/__init__.py
blackboard/integrations/fastapi_dep.py
blackboard/integrations/langchain.py
blackboard/integrations/llamaindex.py
blackboard/persistence/__init__.py
blackboard/persistence/base.py
blackboard/persistence/json_file.py
blackboard/persistence/memory.py
blackboard/persistence/postgres.py
blackboard/persistence/redis.py
blackboard/persistence/sqlite.py
blackboard/serve/__init__.py
blackboard/serve/app.py
blackboard/serve/manager.py
blackboard/stdlib/__init__.py
blackboard/stdlib/workers/__init__.py
blackboard/stdlib/workers/browser.py
blackboard/stdlib/workers/code.py
blackboard/stdlib/workers/human.py
blackboard/stdlib/workers/search.py
blackboard/testing/__init__.py
blackboard/testing/fixtures.py
blackboard/testing/mock_llm.py
blackboard/ui/__init__.py
blackboard/ui/app.py
blackboard/ui/textual_app.py
blackboard_core-1.8.0.dist-info/licenses/LICENSE
blackboard_core-1.8.0.dist-info/METADATA
blackboard_core-1.8.0.dist-info/WHEEL
blackboard_core-1.8.0.dist-info/entry_points.txt
blackboard_core-1.8.0.dist-info/top_level.txt
blackboard_core-1.8.0.dist-info/RECORD
