Metadata-Version: 2.4
Name: blackboard-core
Version: 1.8.0
Summary: A Python SDK implementing the Blackboard Pattern for LLM-powered multi-agent systems
Author: Hemant Singh
License: MIT License
Project-URL: Homepage, https://github.com/hemantsingh443/blackboard-core
Project-URL: Documentation, https://github.com/hemantsingh443/blackboard-core#readme
Project-URL: Repository, https://github.com/hemantsingh443/blackboard-core
Keywords: agents,multi-agent,blackboard,orchestration,llm,ai
Classifier: Development Status :: 5 - Production/Stable
Classifier: Intended Audience :: Developers
Classifier: License :: OSI Approved :: MIT License
Classifier: Programming Language :: Python :: 3
Classifier: Programming Language :: Python :: 3.10
Classifier: Programming Language :: Python :: 3.11
Classifier: Programming Language :: Python :: 3.12
Classifier: Topic :: Software Development :: Libraries :: Python Modules
Requires-Python: >=3.10
License-File: LICENSE
Requires-Dist: pydantic>=2.0.0
Requires-Dist: typing-extensions>=4.0.0
Requires-Dist: litellm>=1.40.0
Requires-Dist: structlog>=24.0.0
Requires-Dist: jinja2>=3.0.0
Provides-Extra: dev
Requires-Dist: pytest>=7.0.0; extra == "dev"
Requires-Dist: pytest-cov>=4.0.0; extra == "dev"
Requires-Dist: pytest-asyncio>=0.23.0; extra == "dev"
Provides-Extra: redis
Requires-Dist: redis>=5.0.0; extra == "redis"
Provides-Extra: chroma
Requires-Dist: chromadb>=0.4.0; extra == "chroma"
Provides-Extra: hybrid
Requires-Dist: rank-bm25>=0.2.2; extra == "hybrid"
Provides-Extra: sqlite
Requires-Dist: aiosqlite>=0.19.0; extra == "sqlite"
Provides-Extra: postgres
Requires-Dist: asyncpg>=0.29.0; extra == "postgres"
Provides-Extra: tui
Requires-Dist: rich>=13.0.0; extra == "tui"
Provides-Extra: textual-tui
Requires-Dist: textual>=0.90.0; extra == "textual-tui"
Provides-Extra: mcp
Requires-Dist: mcp[cli]>=1.0.0; extra == "mcp"
Provides-Extra: telemetry
Requires-Dist: opentelemetry-api>=1.20.0; extra == "telemetry"
Requires-Dist: opentelemetry-sdk>=1.20.0; extra == "telemetry"
Requires-Dist: opentelemetry-exporter-otlp>=1.20.0; extra == "telemetry"
Provides-Extra: langchain
Requires-Dist: langchain-core>=0.3.0; extra == "langchain"
Provides-Extra: llamaindex
Requires-Dist: llama-index-core>=0.14.0; extra == "llamaindex"
Provides-Extra: all
Requires-Dist: redis>=5.0.0; extra == "all"
Requires-Dist: chromadb>=0.4.0; extra == "all"
Requires-Dist: rank-bm25>=0.2.2; extra == "all"
Requires-Dist: aiosqlite>=0.19.0; extra == "all"
Requires-Dist: asyncpg>=0.29.0; extra == "all"
Requires-Dist: rich>=13.0.0; extra == "all"
Requires-Dist: textual>=0.90.0; extra == "all"
Requires-Dist: mcp[cli]>=1.0.0; extra == "all"
Requires-Dist: networkx>=3.0.0; extra == "all"
Requires-Dist: opentelemetry-api>=1.20.0; extra == "all"
Requires-Dist: opentelemetry-sdk>=1.20.0; extra == "all"
Requires-Dist: opentelemetry-exporter-otlp>=1.20.0; extra == "all"
Requires-Dist: langchain-core>=0.3.0; extra == "all"
Requires-Dist: llama-index-core>=0.14.0; extra == "all"
Provides-Extra: serve
Requires-Dist: fastapi>=0.104.0; extra == "serve"
Requires-Dist: uvicorn[standard]>=0.24.0; extra == "serve"
Requires-Dist: sse-starlette>=1.8.0; extra == "serve"
Provides-Extra: browser
Requires-Dist: playwright>=1.40.0; extra == "browser"
Provides-Extra: stdlib
Requires-Dist: httpx>=0.25.0; extra == "stdlib"
Provides-Extra: graph
Requires-Dist: networkx>=3.0.0; extra == "graph"
Provides-Extra: ui
Requires-Dist: streamlit>=1.28.0; extra == "ui"
Requires-Dist: httpx>=0.25.0; extra == "ui"
Dynamic: license-file
